rocket_snake/__init__.py
rocket_snake/basic_requests.py
rocket_snake/client.py
rocket_snake/constants.py
rocket_snake/custom_exceptions.py
rocket_snake/data_classes.py
rocket_snake-0.1.5.dist-info/DESCRIPTION.rst
rocket_snake-0.1.5.dist-info/METADATA
rocket_snake-0.1.5.dist-info/RECORD
rocket_snake-0.1.5.dist-info/WHEEL
rocket_snake-0.1.5.dist-info/metadata.json
rocket_snake-0.1.5.dist-info/top_level.txt
