Metadata-Version: 2.0
Name: rocket-snake
Version: 0.1.5
Summary: Rocket Snake is a client library to access the rocketleaguestats.com API in python with async code.
Home-page: https://github.com/drummersbrother/rocket_snake
Author: Hugo Berg
Author-email: ilykxar@gmail.com
License: Apache
Keywords: rocket_snake
Platform: UNKNOWN
Classifier: Development Status :: 4 - Beta
Classifier: Intended Audience :: Developers
Classifier: License :: OSI Approved :: Apache Software License
Classifier: Natural Language :: English
Classifier: Programming Language :: Python :: 3
Classifier: Programming Language :: Python :: 3.5
Classifier: Programming Language :: Python :: 3.6
Requires-Dist: aiodns (>=1.1.1)
Requires-Dist: aiohttp (>=2.2.3)
Requires-Dist: apiwrapper
Requires-Dist: async-timeout (>=1.2.1)
Requires-Dist: asyncio (>=3.4.3)
Requires-Dist: chardet (>=3.0.4)
Requires-Dist: multidict (>=3.1.3)
Requires-Dist: pycares (>=2.3.0)
Requires-Dist: yarl (>=0.12.0)
